battmo/__init__.py
battmo/julia_import.py
battmo/juliapkg.json
battmo/api/__init__.py
battmo/api/input.py
battmo/api/models.py
battmo/api/output.py
battmo/api/plotting.py
battmo/api/solve.py
battmo/api/tools.py
battmo-0.2.3.dist-info/licenses/LICENSE
battmo-0.2.3.dist-info/METADATA
battmo-0.2.3.dist-info/WHEEL
battmo-0.2.3.dist-info/top_level.txt
battmo-0.2.3.dist-info/RECORD
